CHANGES.txt
README.txt
setup.py
cc/__init__.py
cc.buildout_reports.egg-info/PKG-INFO
cc.buildout_reports.egg-info/SOURCES.txt
cc.buildout_reports.egg-info/dependency_links.txt
cc.buildout_reports.egg-info/entry_points.txt
cc.buildout_reports.egg-info/namespace_packages.txt
cc.buildout_reports.egg-info/not-zip-safe
cc.buildout_reports.egg-info/requires.txt
cc.buildout_reports.egg-info/top_level.txt
cc/buildout_reports/XXXreport2html.py
cc/buildout_reports/__init__.py
cc/buildout_reports/xxx.py
cc/buildout_reports/xxx_report.sh
