Metadata-Version: 1.0
Name: cc.buildout-reports
Version: 0.1
Summary: Recipes for generating developer reports with zc.buildout.
Home-page: http://python.org/pypi/cc.buildout_reports/
Author: Nathan R. Yergler
Author-email: nathan@creativecommons.org
License: ZPL 2.1
Keywords: development build tools buildout
Platform: UNKNOWN
Classifier: Framework :: Buildout
Classifier: Development Status :: 4 - Beta
Classifier: Intended Audience :: Developers
Classifier: License :: OSI Approved :: Zope Public License
Classifier: Topic :: Software Development :: Build Tools
Classifier: Topic :: Software Development :: Libraries :: Python Modules
